themis/__init__.py
themis/_version.py
themis/api.py
themis/py.typed
themis/backends/__init__.py
themis/backends/execution.py
themis/backends/storage.py
themis/cli/__init__.py
themis/cli/__main__.py
themis/cli/main.py
themis/cli/new_project.py
themis/cli/utils.py
themis/cli/commands/__init__.py
themis/cli/commands/benchmarks.py
themis/cli/commands/comparison.py
themis/cli/commands/config_commands.py
themis/cli/commands/cost.py
themis/cli/commands/demo.py
themis/cli/commands/info.py
themis/cli/commands/leaderboard.py
themis/cli/commands/math_benchmarks.py
themis/cli/commands/mcq_benchmarks.py
themis/cli/commands/results.py
themis/cli/commands/sample_run.py
themis/cli/commands/visualize.py
themis/comparison/__init__.py
themis/comparison/engine.py
themis/comparison/reports.py
themis/comparison/statistics.py
themis/config/__init__.py
themis/config/loader.py
themis/config/registry.py
themis/config/runtime.py
themis/config/schema.py
themis/core/__init__.py
themis/core/conversation.py
themis/core/entities.py
themis/core/serialization.py
themis/core/tools.py
themis/core/types.py
themis/datasets/__init__.py
themis/datasets/base.py
themis/datasets/commonsense_qa.py
themis/datasets/competition_math.py
themis/datasets/coqa.py
themis/datasets/gpqa.py
themis/datasets/gsm8k.py
themis/datasets/gsm_symbolic.py
themis/datasets/math500.py
themis/datasets/med_qa.py
themis/datasets/medmcqa.py
themis/datasets/mmlu_pro.py
themis/datasets/piqa.py
themis/datasets/registry.py
themis/datasets/schema.py
themis/datasets/sciq.py
themis/datasets/social_i_qa.py
themis/datasets/super_gpqa.py
themis/evaluation/__init__.py
themis/evaluation/conditional.py
themis/evaluation/math_verify_utils.py
themis/evaluation/pipeline.py
themis/evaluation/reports.py
themis/evaluation/extractors/__init__.py
themis/evaluation/extractors/error_taxonomy_extractor.py
themis/evaluation/extractors/exceptions.py
themis/evaluation/extractors/identity_extractor.py
themis/evaluation/extractors/json_field_extractor.py
themis_eval-0.2.3.dist-info/licenses/LICENSE
themis_eval-0.2.3.dist-info/METADATA
themis_eval-0.2.3.dist-info/WHEEL
themis_eval-0.2.3.dist-info/top_level.txt
themis_eval-0.2.3.dist-info/RECORD
