Metadata-Version: 2.4
Name: themis-eval
Version: 0.2.3
Summary: Lightweight evaluation platform for LLM experiments
Author: Pittawat Taveekitworachai
License: MIT
Project-URL: Resources, https://github.com/Pittawat2542/themis
Project-URL: Homepage, https://pittawat2542.github.io/themis/
Classifier: Development Status :: 3 - Alpha
Classifier: Intended Audience :: Developers
Classifier: Intended Audience :: Science/Research
Classifier: License :: OSI Approved :: MIT License
Classifier: Programming Language :: Python :: 3.12
Classifier: Topic :: Scientific/Engineering :: Artificial Intelligence
Requires-Python: >=3.12
License-File: LICENSE
Requires-Dist: pydantic>=2.12.5
Requires-Dist: cyclopts>=4.0.0
Requires-Dist: hydra-core>=1.3
Requires-Dist: tqdm>=4.67
Requires-Dist: httpx>=0.27
Requires-Dist: litellm>=1.81.0
Requires-Dist: tabulate>=0.9.0
Requires-Dist: tenacity>=9.1.2
Requires-Dist: plotly>=6.5.0
Requires-Dist: math-verify>=0.8.0
Requires-Dist: rich>=14.2.0
Provides-Extra: dev
Requires-Dist: pytest>=8.0; extra == "dev"
Requires-Dist: pytest-cov>=6.0.0; extra == "dev"
Requires-Dist: pytest-timeout>=2.3.1; extra == "dev"
Requires-Dist: pytest-asyncio>=0.24.0; extra == "dev"
Requires-Dist: ruff>=0.8.5; extra == "dev"
Requires-Dist: mypy>=1.14.0; extra == "dev"
Provides-Extra: math
Requires-Dist: datasets>=2.20.0; extra == "math"
Requires-Dist: math-verify>=0.8.0; extra == "math"
Provides-Extra: nlp
Requires-Dist: sacrebleu>=2.4.0; extra == "nlp"
Requires-Dist: rouge-score>=0.1.2; extra == "nlp"
Requires-Dist: bert-score>=0.3.13; extra == "nlp"
Requires-Dist: nltk>=3.8.0; extra == "nlp"
Provides-Extra: code
Requires-Dist: codebleu>=0.7.0; extra == "code"
Provides-Extra: viz
Requires-Dist: plotly>=5.18.0; extra == "viz"
Provides-Extra: server
Requires-Dist: fastapi>=0.128.0; extra == "server"
Requires-Dist: uvicorn[standard]>=0.32.0; extra == "server"
Requires-Dist: websockets>=14.0; extra == "server"
Provides-Extra: docs
Requires-Dist: mkdocs>=1.6.0; extra == "docs"
Requires-Dist: mkdocs-material>=9.5.0; extra == "docs"
Requires-Dist: mkdocstrings[python]>=0.25.0; extra == "docs"
Provides-Extra: all
Requires-Dist: themis-eval[code,docs,math,nlp,server,viz]; extra == "all"
Dynamic: license-file
